setup.py
crftools/__init__.py
crftools/parse.py
crftools.egg-info/PKG-INFO
crftools.egg-info/SOURCES.txt
crftools.egg-info/dependency_links.txt
crftools.egg-info/top_level.txt