Metadata-Version: 1.0
Name: crftools
Version: 0.0.3.4
Summary: useful for CRF++
Home-page: UNKNOWN
Author: Chenliang Wang
Author-email: chenliangwang08ms@gmail.com
License: MIT License
Keywords: crf predict check
Platform: any
